pqbeam/__init__.py
pqbeam-0.0.1.dist-info/METADATA
pqbeam-0.0.1.dist-info/WHEEL
pqbeam-0.0.1.dist-info/RECORD
