Metadata-Version: 2.4
Name: pqbeam
Version: 0.0.1
Summary: pqbeam coming soon
Author: Richard
License-Expression: MIT
